arsalan_sum/__init__.py
arsalan_sum-0.0.1.dist-info/LICENCE.txt
arsalan_sum-0.0.1.dist-info/METADATA
arsalan_sum-0.0.1.dist-info/WHEEL
arsalan_sum-0.0.1.dist-info/top_level.txt
arsalan_sum-0.0.1.dist-info/RECORD
