Metadata-Version: 2.1
Name: arsalan-sum
Version: 0.0.1
Summary: adding number
Home-page: UNKNOWN
Author: Arsalan Yousuf
Author-email: arsalan98y@gmail.com
License: UNKNOWN
Platform: UNKNOWN
Classifier: Programming Language :: Python :: 3
Classifier: License :: OSI Approved :: MIT License
Classifier: Operating System :: OS Independent
